ncm_converter_mcp/__init__.py
ncm_converter_mcp/__main__.py
ncm_converter_mcp/server.py
ncm_converter_mcp-1.0.2.dist-info/METADATA
ncm_converter_mcp-1.0.2.dist-info/WHEEL
ncm_converter_mcp-1.0.2.dist-info/entry_points.txt
ncm_converter_mcp-1.0.2.dist-info/RECORD
