Metadata-Version: 2.4
Name: ncm-converter-mcp
Version: 1.0.2
Summary: Netease Cloud Music .ncm audio converter MCP server based on ncmdump-py
Author-email: NCM Converter MCP <dev@example.com>
License: MIT
Classifier: Development Status :: 4 - Beta
Classifier: Intended Audience :: Developers
Classifier: License :: OSI Approved :: MIT License
Classifier: Programming Language :: Python :: 3
Classifier: Programming Language :: Python :: 3.10
Classifier: Programming Language :: Python :: 3.11
Classifier: Programming Language :: Python :: 3.12
Requires-Python: >=3.10
Requires-Dist: mcp>=1.0.0
Requires-Dist: ncmdump-py>=1.1.6
